{
  "dashboards": {
    "recepciones": [],
    "produccion": [],
    "bandejas": [],
    "stock": [],
    "containers": [],
    "relacion_comercial": [
      "fhorst@riofuturo.cl",
      "vdominguez@riofuturo.cl",
      "vpa@riofuturo.cl",
      "mjaramillo@riofuturo.cl"
    ],
    "finanzas": [
      "jvidaurre@riofuturo.cl",
      "fhorst@riofuturo.cl"
    ],
    "compras": [
      "jbrandt@riofuturo.cl",
      "jvidaurre@riofuturo.cl"
    ],
    "permisos": [
      "mvalladares@riofuturo.cl"
    ],
    "automatizaciones": [],
    "rendimiento": []
  },
  "admins": [
    "mvalladares@riofuturo.cl"
  ],
  "pages": {
    "recepciones.aprobaciones_mp": [
      "ctapia@riofuturo.cl",
      "asesorias@riofuturo.cl"
    ],
    "recepciones.curva_abastecimiento": [
      "fbravo@riofuturo.cl",
      "jvidaurre@riofuturo.cl",
      "msepulveda@riofuturo.cl"
    ]
  },
  "maintenance": {
    "enabled": true,
    "message": "El sistema está siendo ajustado en este momento."
  }
}